odoo/addons/sale_order_line_delivery_state/README.rst
odoo/addons/sale_order_line_delivery_state/__init__.py
odoo/addons/sale_order_line_delivery_state/__manifest__.py
odoo/addons/sale_order_line_delivery_state/i18n/es.po
odoo/addons/sale_order_line_delivery_state/i18n/it.po
odoo/addons/sale_order_line_delivery_state/i18n/sale_order_line_delivery_state.pot
odoo/addons/sale_order_line_delivery_state/models/__init__.py
odoo/addons/sale_order_line_delivery_state/models/sale_order_line.py
odoo/addons/sale_order_line_delivery_state/readme/CONTRIBUTORS.rst
odoo/addons/sale_order_line_delivery_state/readme/DESCRIPTION.rst
odoo/addons/sale_order_line_delivery_state/static/description/icon.png
odoo/addons/sale_order_line_delivery_state/static/description/index.html
odoo/addons/sale_order_line_delivery_state/tests/__init__.py
odoo/addons/sale_order_line_delivery_state/tests/test_sale_line_delivery_state.py
odoo/addons/sale_order_line_delivery_state/views/sale_order_line_views.xml
odoo/addons/sale_order_line_delivery_state/views/sale_order_views.xml
odoo14_addon_sale_order_line_delivery_state-14.0.1.1.0.dist-info/METADATA
odoo14_addon_sale_order_line_delivery_state-14.0.1.1.0.dist-info/WHEEL
odoo14_addon_sale_order_line_delivery_state-14.0.1.1.0.dist-info/top_level.txt
odoo14_addon_sale_order_line_delivery_state-14.0.1.1.0.dist-info/RECORD
